{
	"ID": "icons-group07",
	"name": "Icons-Group 7",
	"description": "<span class='icon icon-size-sm icon-atm'></span> <span class='icon icon-size-sm icon-calculator'></span> <span class='icon icon-size-sm icon-calendar'></span> <span class='icon icon-size-sm icon-camera'></span> <span class='icon icon-size-sm icon-message'></span> <span class='icon icon-size-sm icon-mobile-pay'></span> <span class='icon icon-size-sm icon-notification'></span> <span class='icon icon-size-sm icon-paypass'></span> <span class='icon icon-size-sm icon-quick-balance'></span> <span class='icon icon-size-sm icon-service-bell'></span> <span class='icon icon-size-sm icon-settings'></span> <span class='icon icon-size-sm icon-shelf-menu'></span> <span class='icon icon-size-sm icon-to-mobile'></span>",
	"category": "Icons",
	"versions": {
		"1.0.0": {
			"dependencies": [
				"icons-base"
			],
			"js": false,
			"less": false,
			"svg": true,
			"font": false,
			"size": 39
		}
	},
	"hash": "d2a5f2f7ec5e2ece67d4f02aca8e5a6c212c043a"
}