{
	"ID": "icons-group15",
	"name": "Icons-Group 15",
	"description": "<span class='icon icon-size-sm icon-book'></span> <span class='icon icon-size-sm icon-compass'></span> <span class='icon icon-size-sm icon-cross'></span> <span class='icon icon-size-sm icon-cube'></span> <span class='icon icon-size-sm icon-global'></span> <span class='icon icon-size-sm icon-idea'></span> <span class='icon icon-size-sm icon-key'></span> <span class='icon icon-size-sm icon-more'></span> <span class='icon icon-size-sm icon-umbrella'></span> <span class='icon icon-size-sm icon-wallet'></span>",
	"category": "Icons",
	"versions": {
		"1.0.0": {
			"dependencies": [
				"icons-base"
			],
			"js": false,
			"less": false,
			"svg": true,
			"font": false,
			"size": 21,
			"brands": [
				"BOM",
				"BSA",
				"STG",
				"WBC"
			]
		},
		"1.0.1": {
			"dependencies": [
				"_colors:1.0.1",
				"icons-base"
			],
			"js": false,
			"less": false,
			"svg": true,
			"font": false,
			"size": 21,
			"brands": [
				"BOM",
				"BSA",
				"STG",
				"WBC"
			]
		},
		"1.0.2": {
			"dependencies": [
				"_colors:1.0.1",
				"icons-base"
			],
			"js": false,
			"less": false,
			"svg": true,
			"font": false,
			"size": 21,
			"brands": [
				"BOM",
				"BSA",
				"STG",
				"WBC"
			]
		},
		"2.0.0": {
			"dependencies": [
				"_colors:1.0.1",
				"icons-base"
			],
			"js": false,
			"less": false,
			"svg": true,
			"font": false,
			"size": 21,
			"brands": [
				"BOM",
				"BSA",
				"STG",
				"WBC",
				"WBG",
				"BT"
			]
		},
		"2.0.1": {
			"dependencies": [
				"_colors:1.0.1",
				"icons-base"
			],
			"js": false,
			"less": false,
			"svg": true,
			"font": false,
			"size": 20,
			"brands": [
				"BOM",
				"BSA",
				"STG",
				"WBC",
				"WBG",
				"BT"
			]
		}
	},
	"hash": "b50b536491bd310d15a052efb39e77ea"
}