{
	"ID": "form-base",
	"name": "Form Base",
	"description": "General form styling; providing form structure, layout and grouped input styling",
	"category": "Forms",
	"versions": {
		"1.0.0": {
			"dependencies": [],
			"js": false,
			"less": true,
			"svg": false,
			"font": false,
			"size": 6,
			"brands": [
				"BOM",
				"BSA",
				"STG",
				"WBC",
				"WBG",
				"BT"
			]
		},
		"1.0.1": {
			"dependencies": [],
			"js": false,
			"less": true,
			"svg": true,
			"font": false,
			"size": 7,
			"brands": [
				"BOM",
				"BSA",
				"STG",
				"WBC",
				"WBG",
				"BT"
			]
		}
	},
	"hash": "a6394ac3dc2fba53cf7cf2e289d495c5"
}